easyload/__init__.py
easyload/built_excel.py
easyload/easy_load_data.py
easyload/easy_save_data.py
easyload/load_any_json.py
easyload-1.0.9.dist-info/LICENSE
easyload-1.0.9.dist-info/METADATA
easyload-1.0.9.dist-info/WHEEL
easyload-1.0.9.dist-info/top_level.txt
easyload-1.0.9.dist-info/RECORD
