Metadata-Version: 2.1
Name: easyload
Version: 1.0.9
Summary: A Python library for loading multiple types of data
Home-page: https://github.com/shoe-maker/easyload
Author: Hanshuang Tong
Author-email: tonghanshuang.thu@gmail.com
Project-URL: Bug Reports, https://github.com/shoe-maker/easyload/issues
Project-URL: Source, https://github.com/shoe-maker/easyload/
Keywords: easy load data
Classifier: Development Status :: 3 - Alpha
Classifier: Intended Audience :: Developers
Classifier: Topic :: Software Development :: Build Tools
Classifier: License :: OSI Approved :: MIT License
Classifier: Programming Language :: Python :: 3.6
Requires-Python: >=3.6
License-File: LICENSE
Requires-Dist: xlwt
Requires-Dist: numpy
Requires-Dist: pandas
